{
	"forms": {
		"Entry": {
			"timeStamp": "2022-08-15T21:14:05.832Z",
			"destination": "detailScreen"
		},
		"ListBox": {
			"timeStamp": "2022-08-15T21:14:05.835Z",
			"destination": "detailScreen"
		},
		"subform": {
			"timeStamp": "2022-08-15T21:14:05.846Z",
			"destination": "detailScreen"
		},
		"print": {
			"timeStamp": "2022-08-15T21:14:05.845Z",
			"destination": "listPrinter"
		},
		"list": {
			"timeStamp": "2022-08-15T21:14:05.843Z",
			"destination": "listScreen"
		},
		"View": {
			"timeStamp": "2022-08-15T21:14:05.842Z",
			"destination": "detailScreen"
		}
	}
}