<?xml version="1.0" encoding="UTF-8" standalone="yes" ?><XML_Bag Ver="1.50">  <User_Content>    <config>      <createdate Type="Date">2021-08-18T00:00:00</createdate>      <createtime Type="Time">18:56:54</createtime>      <type Type="Text">Test-CUSTOM</type>      <enabled Type="Boolean">0</enabled>      <modifydate Type="Date">2021-08-18T00:00:00</modifydate>      <modifytime Type="Time">18:56:57</modifytime>    </config>    <site>      <identifier Type="Text">Test</identifier>      <password Type="Text">password</password>      <offset Type="Long">0</offset>      <syncidfield Type="Text">_Sync_ID</syncidfield>      <syncdatafield Type="Text">_Sync_Data</syncdatafield>      <synchashfield Type="Text">_Sync_Hash</synchashfield>      <synccontrolmethod Type="Text">SYNC_This</synccontrolmethod>      <timeserver>        <active Type="Boolean">1</active>        <zone Type="Long">-8</zone>        <links Array_Value="0" Type="ArrayText">          <Element N="0"/>          <Element N="1">time-nw.nist.gov</Element>          <Element N="2">nist1-sj.WiTime.net</Element>          <Element N="3">nist1-ny.WiTime.net</Element>          <Element N="4">time-a.timefreq.bldrdoc.gov</Element>          <Element N="5">time-b.timefreq.bldrdoc.gov</Element>          <Element N="6">time-c.timefreq.bldrdoc.gov</Element>        </links>        <comments Array_Value="0" Type="ArrayText">          <Element N="0"/>          <Element N="1">Microsoft, Redmond, Washington</Element>          <Element N="2">WiTime, San Jose, California</Element>          <Element N="3">WiTime, New York City</Element>          <Element N="4">NIST, Boulder, Colorado</Element>          <Element N="5">NIST, Boulder, Colorado</Element>          <Element N="6">NIST, Boulder, Colorado</Element>        </comments>      </timeserver>      <autovalidate Type="Long">1</autovalidate>      <syncdeleteexceptions Type="Text">[Registers]</syncdeleteexceptions>      <forcesyncid Type="Boolean">1</forcesyncid>      <usedeleteflag Type="Boolean">0</usedeleteflag>      <autopull Type="Long">0</autopull>    </site>    <sequence>      <active Type="Boolean">0</active>      <interval Type="Long">15</interval>      <redistribute Type="Boolean">0</redistribute>    </sequence>    <send>      <interval Type="Long">5</interval>      <requestsize Type="Long">128</requestsize>      <compression Type="Text">None</compression>      <timeout Type="Long">60</timeout>      <httpkeepalive Type="Boolean">0</httpkeepalive>      <suspendinterval Type="Long">15</suspendinterval>      <encrypt Type="Boolean">0</encrypt>    </send>    <remotesite>      <identifier Array_Value="0" Type="ArrayText">        <Element N="0"/>        <Element N="1">Test</Element>      </identifier>      <password Array_Value="0" Type="ArrayText">        <Element N="0"/>        <Element N="1">password</Element>      </password>      <url Array_Value="0" Type="ArrayText">        <Element N="0"/>        <Element N="1">http://192.168.1.100:8080/4DSoap/</Element>      </url>      <send Array_Value="0" Type="ArrayBoolean">        <Element N="0">0</Element>        <Element N="1">0</Element>      </send>      <receive Array_Value="0" Type="ArrayBoolean">        <Element N="0">0</Element>        <Element N="1">0</Element>      </receive>      <suspenddts Array_Value="0" Type="ArrayText">        <Element N="0"/>        <Element N="1"/>      </suspenddts>    </remotesite>    <log>      <receive>        <level Type="Long">1</level>        <path Type="Text">Mac02-HD:Backups:CXR7:V18:DataFile_Generic:Logs:Sync:Sync_Recv_Log.txt</path>      </receive>      <send>        <level Type="Long">1</level>        <path Type="Text">Mac02-HD:Backups:CXR7:V18:DataFile_Generic:Logs:Sync:Sync_Send_Log.txt</path>      </send>    </log>    <soap>      <action Type="Text">cxr_WebService#Sync_Receive_WS</action>      <method Type="Text">Sync_Receive_WS</method>      <namespace Type="Text">http://www.clearviewsys.com/namespace/default</namespace>    </soap>    <deletecontrol>      <tablename Array_Value="0" Type="ArrayText">        <Element N="0"/>        <Element N="1">_TableTemplate</Element>        <Element N="2">AccountInOuts</Element>        <Element N="3">Accounts</Element>        <Element N="4">Addresses</Element>        <Element N="5">Agents</Element>        <Element N="6">AML_AggrRules</Element>        <Element N="7">AML_Alerts</Element>        <Element N="8">AML_Reports</Element>        <Element N="9">AML_ReviewLog</Element>        <Element N="10">AML_RiskTemplates</Element>        <Element N="11">AMLRules</Element>        <Element N="12">Bookings</Element>        <Element N="13">Branches</Element>        <Element N="14">CalendarEvents</Element>        <Element N="15">CallLogs</Element>        <Element N="16">CashInOuts</Element>        <Element N="17">CashInventory</Element>        <Element N="18">CashTransactions</Element>        <Element N="19">CC_Log</Element>        <Element N="20">Cheques</Element>        <Element N="21">Cities</Element>        <Element N="22">CommonLists</Element>        <Element N="23">CompanyTypes</Element>        <Element N="24">Countries</Element>        <Element N="25">CSMRelations</Element>        <Element N="26">Currencies</Element>        <Element N="27">Customers</Element>        <Element N="28">Customers2</Element>        <Element N="29">CustomerTypes</Element>        <Element N="30">Denominations</Element>        <Element N="31">eWires</Element>        <Element N="32">ExceptionsLog</Element>        <Element N="33">FeeRules</Element>        <Element N="34">FeeStructures</Element>        <Element N="35">FieldConstraints</Element>        <Element N="36">FormObjects</Element>        <Element N="37">FTP_Sites</Element>        <Element N="38">IM_KYCLog</Element>        <Element N="39">IM_TransferLog</Element>        <Element N="40">Industries</Element>        <Element N="41">Invoices</Element>        <Element N="42">ItemInOuts</Element>        <Element N="43">Items</Element>        <Element N="44">KeyValues</Element>        <Element N="45">KYC_ReviewLog</Element>        <Element N="46">KYC2020Log</Element>        <Element N="47">Licenses</Element>        <Element N="48">LinkedDocs</Element>        <Element N="49">Links</Element>        <Element N="50">List_Banks</Element>        <Element N="51">List_PIN</Element>        <Element N="52">List_POT</Element>        <Element N="53">List_Relationships</Element>        <Element N="54">List_RiskFactors</Element>        <Element N="55">List_SOF</Element>        <Element N="56">MainAccounts</Element>        <Element N="57">mchk_CheckLog</Element>        <Element N="58">NoteTemplates</Element>        <Element N="59">Notifications</Element>        <Element N="60">Occupations</Element>        <Element N="61">OrderLines</Element>        <Element N="62">Orders</Element>        <Element N="63">PaymentTypes</Element>        <Element N="64">PictureIDTypes</Element>        <Element N="65">Privileges</Element>        <Element N="66">RateRules</Element>        <Element N="67">Registers</Element>        <Element N="68">Relations</Element>        <Element N="69">Reports</Element>        <Element N="70">SanctionCheckLog</Element>        <Element N="71">SanctionLists</Element>        <Element N="72">ShipmentLines</Element>        <Element N="73">Shipments</Element>        <Element N="74">Signatures</Element>        <Element N="75">States</Element>        <Element N="76">SubAccounts</Element>        <Element N="77">Tags</Element>        <Element N="78">TellerProof</Element>        <Element N="79">TellerProofLines</Element>        <Element N="80">ThirdParties</Element>        <Element N="81">TransactionTypes</Element>        <Element N="82">TransferTemplates</Element>        <Element N="83">User_Log</Element>        <Element N="84">UserPasswords</Element>        <Element N="85">Users</Element>        <Element N="86">WebEWires</Element>        <Element N="87">WebUsers</Element>        <Element N="88">Wires</Element>        <Element N="89">WireTemplates</Element>      </tablename>      <tablenumber Array_Value="0" Type="ArrayReal">        <Element N="0">0</Element>        <Element N="1">90</Element>        <Element N="2">37</Element>        <Element N="3">9</Element>        <Element N="4">147</Element>        <Element N="5">22</Element>        <Element N="6">150</Element>        <Element N="7">137</Element>        <Element N="8">119</Element>        <Element N="9">125</Element>        <Element N="10">138</Element>        <Element N="11">74</Element>        <Element N="12">50</Element>        <Element N="13">70</Element>        <Element N="14">80</Element>        <Element N="15">51</Element>        <Element N="16">32</Element>        <Element N="17">35</Element>        <Element N="18">36</Element>        <Element N="19">135</Element>        <Element N="20">1</Element>        <Element N="21">60</Element>        <Element N="22">84</Element>        <Element N="23">161</Element>        <Element N="24">62</Element>        <Element N="25">89</Element>        <Element N="26">6</Element>        <Element N="27">3</Element>        <Element N="28">155</Element>        <Element N="29">94</Element>        <Element N="30">31</Element>        <Element N="31">13</Element>        <Element N="32">75</Element>        <Element N="33">59</Element>        <Element N="34">38</Element>        <Element N="35">69</Element>        <Element N="36">120</Element>        <Element N="37">152</Element>        <Element N="38">144</Element>        <Element N="39">133</Element>        <Element N="40">114</Element>        <Element N="41">5</Element>        <Element N="42">40</Element>        <Element N="43">39</Element>        <Element N="44">115</Element>        <Element N="45">124</Element>        <Element N="46">159</Element>        <Element N="47">160</Element>        <Element N="48">4</Element>        <Element N="49">17</Element>        <Element N="50">134</Element>        <Element N="51">130</Element>        <Element N="52">128</Element>        <Element N="53">136</Element>        <Element N="54">132</Element>        <Element N="55">129</Element>        <Element N="56">28</Element>        <Element N="57">142</Element>        <Element N="58">140</Element>        <Element N="59">158</Element>        <Element N="60">2</Element>        <Element N="61">96</Element>        <Element N="62">95</Element>        <Element N="63">116</Element>        <Element N="64">92</Element>        <Element N="65">24</Element>        <Element N="66">157</Element>        <Element N="67">10</Element>        <Element N="68">154</Element>        <Element N="69">73</Element>        <Element N="70">111</Element>        <Element N="71">113</Element>        <Element N="72">98</Element>        <Element N="73">97</Element>        <Element N="74">141</Element>        <Element N="75">61</Element>        <Element N="76">112</Element>        <Element N="77">162</Element>        <Element N="78">78</Element>        <Element N="79">79</Element>        <Element N="80">101</Element>        <Element N="81">93</Element>        <Element N="82">54</Element>        <Element N="83">146</Element>        <Element N="84">145</Element>        <Element N="85">25</Element>        <Element N="86">149</Element>        <Element N="87">14</Element>        <Element N="88">8</Element>        <Element N="89">42</Element>      </tablenumber>      <allowdelete Array_Value="0" Type="ArrayBoolean">        <Element N="0">0</Element>        <Element N="1">0</Element>        <Element N="2">0</Element>        <Element N="3">0</Element>        <Element N="4">0</Element>        <Element N="5">0</Element>        <Element N="6">0</Element>        <Element N="7">0</Element>        <Element N="8">0</Element>        <Element N="9">0</Element>        <Element N="10">0</Element>        <Element N="11">0</Element>        <Element N="12">0</Element>        <Element N="13">0</Element>        <Element N="14">0</Element>        <Element N="15">0</Element>        <Element N="16">0</Element>        <Element N="17">0</Element>        <Element N="18">0</Element>        <Element N="19">0</Element>        <Element N="20">0</Element>        <Element N="21">0</Element>        <Element N="22">0</Element>        <Element N="23">0</Element>        <Element N="24">0</Element>        <Element N="25">0</Element>        <Element N="26">0</Element>        <Element N="27">0</Element>        <Element N="28">0</Element>        <Element N="29">0</Element>        <Element N="30">0</Element>        <Element N="31">0</Element>        <Element N="32">0</Element>        <Element N="33">0</Element>        <Element N="34">0</Element>        <Element N="35">0</Element>        <Element N="36">0</Element>        <Element N="37">0</Element>        <Element N="38">0</Element>        <Element N="39">0</Element>        <Element N="40">0</Element>        <Element N="41">0</Element>        <Element N="42">0</Element>        <Element N="43">0</Element>        <Element N="44">0</Element>        <Element N="45">0</Element>        <Element N="46">0</Element>        <Element N="47">0</Element>        <Element N="48">0</Element>        <Element N="49">0</Element>        <Element N="50">0</Element>        <Element N="51">0</Element>        <Element N="52">0</Element>        <Element N="53">0</Element>        <Element N="54">0</Element>        <Element N="55">0</Element>        <Element N="56">0</Element>        <Element N="57">0</Element>        <Element N="58">0</Element>        <Element N="59">0</Element>        <Element N="60">0</Element>        <Element N="61">0</Element>        <Element N="62">0</Element>        <Element N="63">0</Element>        <Element N="64">0</Element>        <Element N="65">0</Element>        <Element N="66">0</Element>        <Element N="67">0</Element>        <Element N="68">0</Element>        <Element N="69">0</Element>        <Element N="70">0</Element>        <Element N="71">0</Element>        <Element N="72">0</Element>        <Element N="73">0</Element>        <Element N="74">0</Element>        <Element N="75">0</Element>        <Element N="76">0</Element>        <Element N="77">0</Element>        <Element N="78">0</Element>        <Element N="79">0</Element>        <Element N="80">0</Element>        <Element N="81">0</Element>        <Element N="82">0</Element>        <Element N="83">0</Element>        <Element N="84">0</Element>        <Element N="85">0</Element>        <Element N="86">0</Element>        <Element N="87">0</Element>        <Element N="88">0</Element>        <Element N="89">0</Element>      </allowdelete>    </deletecontrol>  </User_Content>  <Record_Content/>  <Bag_Content/></XML_Bag>